llama_index/llms/siliconflow/__init__.py
llama_index/llms/siliconflow/base.py
llama_index_llms_siliconflow-0.4.1.dist-info/METADATA
llama_index_llms_siliconflow-0.4.1.dist-info/WHEEL
llama_index_llms_siliconflow-0.4.1.dist-info/licenses/LICENSE
llama_index_llms_siliconflow-0.4.1.dist-info/RECORD
