Metadata-Version: 2.4
Name: llama-index-llms-siliconflow
Version: 0.4.1
Summary: llama-index llms siliconflow integration
Author: nightosong
License-Expression: MIT
License-File: LICENSE
Requires-Python: <4.0,>=3.9
Requires-Dist: aiohttp<4,>=3.8.6
Requires-Dist: llama-index-core<0.15,>=0.13.0
